fwordlesolver/__init__.py
fwordlesolver/__main__.py
fwordlesolver/data/__init__.py
fwordlesolver/data/sowpods.txt.gz
fwordlesolver/matcher.py
fwordlesolver/solver.py
fwordlesolver-0.3.0.dist-info/METADATA
fwordlesolver-0.3.0.dist-info/WHEEL
fwordlesolver-0.3.0.dist-info/entry_points.txt
fwordlesolver-0.3.0.dist-info/RECORD
