Metadata-Version: 2.3
Name: fwordlesolver
Version: 0.3.0
Summary: Word puzzle solver library and CLI
License: MIT
Keywords: wordle,word,solver,cli,library
Author: Fma
Author-email: info@fmakdemir.com
Requires-Python: >=3.9
Classifier: Development Status :: 3 - Alpha
Classifier: Environment :: Console
Classifier: Intended Audience :: Developers
Classifier: Intended Audience :: Science/Research
Classifier: License :: OSI Approved :: MIT License
Classifier: Natural Language :: English
Classifier: Programming Language :: Python :: 3
Classifier: Programming Language :: Python :: 3.9
Classifier: Programming Language :: Python :: 3.10
Classifier: Programming Language :: Python :: 3.11
Classifier: Programming Language :: Python :: 3.12
Classifier: Programming Language :: Python :: 3.13
Classifier: Topic :: Games/Entertainment
Classifier: Topic :: Games/Entertainment :: Board Games
Classifier: Topic :: Games/Entertainment :: Puzzle Games
Classifier: Topic :: Software Development :: Libraries :: Python Modules
Requires-Dist: typer (>=0.15.0)
Project-URL: Bug Tracker, https://github.com/fmakdemir/wordle-solver/issues
Project-URL: Documentation, https://github.com/fmakdemir/wordle-solver
Project-URL: Homepage, https://github.com/fmakdemir/wordle-solver
Project-URL: Repository, https://github.com/fmakdemir/wordle-solver
